{"title":"Elon Musk โต้ซีอีโอ Waymo บอก Tesla มีฮาร์ดแวร์-ซอฟต์แวร์ AI ที่ดีกว่า","link":"https://www.blognone.com/node/120826","date":1611664089000,"content":"<div class=\"field field-name-body field-type-text-with-summary field-label-hidden\"><div class=\"field-items\"><div class=\"field-item even\"><p>Elon Musk ออกมาตอบโต้ John Krafcik ซีอีโอ Waymo หลัง<a href=\"https://www.blognone.com/node/120790\">มีข่าว</a>ที่เขาบอกว่า Tesla ไม่ใช่คู่แข่งของบริษัทในตลาดรถยนต์ไร้คนขับ โดย Musk ได้<a href=\"https://twitter.com/elonmusk/status/1353564655088619520\">ตอบ</a>ทวีตข่าวดังกล่าวว่า Tesla มีฮาร์ดแวร์และซอฟต์แวร์ AI ที่ดีกว่า Waymo</p>\n<p>Musk ยังปิดท้ายว่า money ซึ่งหมายถึงราคารถของ Waymo ที่สูงกว่า Tesla โดยในบทสัมภาษณ์ Krafcik นั้น เขาบอกว่าราคาจะอยู่ที่ 100,000 ดอลลาร์ขึ้นไป เทียบเคียงกับ Mercedes S-Class ขณะที่ Tesla มีเป้าหมายทำราคารถยนต์ให้เข้าถึงได้มากที่สุด โดยปัจจุบันเริ่มต้นที่ 38,000 ดอลลาร์</p>\n<p>ปัจจุบัน Tesla มีระบบที่เรียกว่า Autopilot แต่บริษัทก็เริ่มออกซอฟต์แวร์ทดสอบในโหมดรถยนต์ขับเคลื่อนเองเต็มรูปแบบ (FSD) ให้กับลูกค้าแบบจำกัดจำนวนตั้งแต่ปลายปีที่แล้ว</p>\n<p>ที่มา: <a href=\"https://www.businessinsider.com/elon-musk-waymo-ceo-self-driving-autopilot-2021-1\">Business Insider</a></p>\n<p><img src=\"https://www.blognone.com/sites/default/files/externals/c90fdf5045a1f4f20e1d512e4c4062b6.jpg\" alt=\"Elon Musk\" /></p>\n<blockquote class=\"twitter-tweet\"><p lang=\"en\" dir=\"ltr\" xml:lang=\"en\">To my surprise, Tesla has better AI hardware &amp; software than Waymo (money)</p>\n<p>— Elon Musk (@elonmusk) <a href=\"https://twitter.com/elonmusk/status/1353564655088619520?ref_src=twsrc%5Etfw\">January 25, 2021</a></p></blockquote>\n</div></div></div><div class=\"field field-name-taxonomy-vocabulary-1 field-type-taxonomy-term-reference field-label-above\"><div class=\"field-label\">Topics:&nbsp;</div><div class=\"field-items\"><div class=\"field-item even\"><a href=\"/topics/elon-musk\">Elon Musk</a></div><div class=\"field-item odd\"><a href=\"/topics/tesla-motors\">Tesla Motors</a></div><div class=\"field-item even\"><a href=\"/topics/waymo\">Waymo</a></div><div class=\"field-item odd\"><a href=\"/topics/self-driving-car\">Self-Driving Car</a></div><div class=\"field-item even\"><a href=\"/topics/automobile\">Automobile</a></div></div></div>","author":"arjin","siteTitle":"Blognone","siteHash":"ededadcf18490b3937e7dd89ebe8c00dc129addbdf1ebe4aff1f458146693da0","entryHash":"0770897156ce8204c9fcd0d083f3399966bd6fa7ae4f3bbd42b6c9fcdc1c7338","category":"Thai"}