{"title":"Twitter Suspends 70,000 QAnon Accounts","link":"https://blog.twitter.com/en_us/topics/company/2021/protecting--the-conversation-following-the-riots-in-washington--.html","date":1610492436000,"content":"\n<p>Twitter Safety:</p>\n\n<blockquote>\n  <p>Given the violent events in Washington, DC, and increased risk of\nharm, we began permanently suspending thousands of accounts that\nwere primarily dedicated to sharing QAnon content on Friday\nafternoon.</p>\n\n<p>Many of the individuals impacted by this updated enforcement\naction held multiple accounts, driving up the total number of\naccounts impacted. Since Friday, more than 70,000 accounts have\nbeen suspended as a result of our efforts, with many instances of\na single individual operating numerous accounts. These accounts\nwere engaged in sharing harmful QAnon-associated content at scale\nand were primarily dedicated to the propagation of this conspiracy\ntheory across the service.</p>\n</blockquote>\n\n<p>Better late than never, again, but they knew these kooks were spreading poison months ago. It’s shocking how many people I know with immediate family members who’ve been consumed by this QAnon conspiracy cult.</p>\n\n<div>\n<a  title=\"Permanent link to ‘Twitter Suspends 70,000 QAnon Accounts’\"  href=\"https://daringfireball.net/linked/2021/01/12/twitter-suspends-qanon\">&nbsp;★&nbsp;</a>\n</div>\n\n\t","author":"John Gruber","siteTitle":"Daring Fireball","siteHash":"fc569638025dadf22a867470f8215f38855cf50e975782a6c989909474292a36","entryHash":"36ed69aca24d01e40358856e2948c7ac7e917ce9e6712652069b2e715a8d0094","category":"Tech"}