{"title":"iPhone 13","link":"https://www.macrumors.com/roundup/iphone-13/","date":1611447794000,"content":"It's early to talk about the 2021 <a href=\"https://www.macrumors.com/guide/iphone/\">iPhone</a>, but rumors are already buzzing about what to expect from the so called <a href=\"https://www.macrumors.com/roundup/iphone-13/\">iPhone 13</a>. Here's what we know so far. \r\n<br/>\r\n\r\n<br/>\r\n<a href=\"https://www.macrumors.com/roundup/iphone-13/\">Click to read our iPhone 13 Roundup</a>.<div class=\"feedflare\">\r\n<a href=\"http://feeds.macrumors.com/~ff/MacRumors-All?a=6coFzU-17ZQ:td0Fr27dxXE:6W8y8wAjSf4\"><img src=\"http://feeds.feedburner.com/~ff/MacRumors-All?d=6W8y8wAjSf4\" border=\"0\"></img></a> <a href=\"http://feeds.macrumors.com/~ff/MacRumors-All?a=6coFzU-17ZQ:td0Fr27dxXE:qj6IDK7rITs\"><img src=\"http://feeds.feedburner.com/~ff/MacRumors-All?d=qj6IDK7rITs\" border=\"0\"></img></a>\r\n</div><img src=\"http://feeds.feedburner.com/~r/MacRumors-All/~4/6coFzU-17ZQ\" height=\"1\" width=\"1\" alt=\"\"/>","author":"Juli Clover","siteTitle":"MacRumors: Mac News and Rumors - All Stories","siteHash":"4c0f1b1ecc2ed084c9f5be50f1058e33a55cdf9b904dadc33a2071fc2d63e8c1","entryHash":"c1927e0c66f6e6a53f9e1d9e1364ea1ace6e6bfc37b8142e4d31bd9a8519dc1c","category":"Apple"}